{
    "name": "Cyberpunk",
    "colors": {
        "bg-primary": "#050510",
        "bg-secondary": "#0a0a1a",
        "bg-tertiary": "#14142a",
        "bg-elevated": "#1c1c38",
        "bg-hover": "#24244a",
        "bg-active": "#2f2f5c",
        "surface-glass": "rgba(10, 10, 26, 0.85)",
        "surface-glass-border": "rgba(255, 0, 128, 0.2)",
        "surface-glass-hover": "rgba(28, 28, 56, 0.9)",
        "text-primary": "#e0e0ff",
        "text-secondary": "#a0a0cc",
        "text-tertiary": "#6b6b99",
        "text-accent": "#ff007f",
        "text-on-accent": "#ffffff",
        "accent-primary": "#f0f",
        "accent-primary-hover": "#ff4df0",
        "accent-primary-glow": "rgba(255, 0, 255, 0.4)",
        "accent-secondary": "#00f0ff",
        "accent-success": "#00ff9d",
        "accent-warning": "#f0db4f",
        "accent-danger": "#ff3366",
        "node-checkpoint": "#00f0ff",
        "node-checkpoint-bg": "rgba(0, 240, 255, 0.1)",
        "node-lora": "#ff007f",
        "node-lora-bg": "rgba(255, 0, 127, 0.1)",
        "node-vae": "#b300ff",
        "node-vae-bg": "rgba(179, 0, 255, 0.1)",
        "node-merge": "#00ff9d",
        "node-merge-bg": "rgba(0, 255, 157, 0.1)",
        "node-output": "#ffb700",
        "node-output-bg": "rgba(255, 183, 0, 0.1)",
        "node-utility": "#6b6b99",
        "node-utility-bg": "rgba(107, 107, 153, 0.1)",
        "conn-model": "#00f0ff",
        "conn-lora": "#ff007f",
        "conn-vae": "#b300ff",
        "canvas-bg": "#020208",
        "canvas-grid": "rgba(0, 240, 255, 0.05)",
        "canvas-grid-major": "rgba(255, 0, 255, 0.08)",
        "border-subtle": "rgba(255, 0, 255, 0.1)",
        "border-default": "rgba(0, 240, 255, 0.2)",
        "border-strong": "rgba(255, 0, 127, 0.4)",
        "border-focus": "#00f0ff"
    }
}
