{
    "name": "Matrix",
    "colors": {
        "bg-primary": "#020a02",
        "bg-secondary": "#051405",
        "bg-tertiary": "#0a240a",
        "bg-elevated": "#0f330f",
        "bg-hover": "#144214",
        "bg-active": "#1c521c",
        "surface-glass": "rgba(5, 20, 5, 0.85)",
        "surface-glass-border": "rgba(0, 255, 64, 0.2)",
        "surface-glass-hover": "rgba(10, 36, 10, 0.9)",
        "text-primary": "#e6ffe6",
        "text-secondary": "#b3ffb3",
        "text-tertiary": "#80ff80",
        "text-accent": "#00ff40",
        "text-on-accent": "#002b0b",
        "accent-primary": "#00e639",
        "accent-primary-hover": "#33ff66",
        "accent-primary-glow": "rgba(0, 230, 57, 0.4)",
        "accent-secondary": "#00ffcc",
        "accent-success": "#33ff33",
        "accent-warning": "#ccff00",
        "accent-danger": "#ff3333",
        "node-checkpoint": "#00e639",
        "node-checkpoint-bg": "rgba(0, 230, 57, 0.1)",
        "node-lora": "#00ccff",
        "node-lora-bg": "rgba(0, 204, 255, 0.1)",
        "node-vae": "#99ff33",
        "node-vae-bg": "rgba(153, 255, 51, 0.1)",
        "node-merge": "#33cc33",
        "node-merge-bg": "rgba(51, 204, 51, 0.1)",
        "node-output": "#ffff00",
        "node-output-bg": "rgba(255, 255, 0, 0.1)",
        "node-utility": "#669966",
        "node-utility-bg": "rgba(102, 153, 102, 0.1)",
        "conn-model": "#00e639",
        "conn-lora": "#00ccff",
        "conn-vae": "#99ff33",
        "canvas-bg": "#010801",
        "canvas-grid": "rgba(0, 230, 57, 0.05)",
        "canvas-grid-major": "rgba(0, 255, 64, 0.08)",
        "border-subtle": "rgba(0, 255, 64, 0.1)",
        "border-default": "rgba(0, 255, 64, 0.2)",
        "border-strong": "rgba(0, 255, 64, 0.4)",
        "border-focus": "#00ff40"
    }
}
